urllib4/__init__.py
urllib4/_base_connection.py
urllib4/_collections.py
urllib4/_version.py
urllib4/connection.py
urllib4/connectionpool.py
urllib4/exceptions.py
urllib4/fields.py
urllib4/filepost.py
urllib4/poolmanager.py
urllib4/response.py
urllib4/http2/__init__.py
urllib4/http2/connection.py
urllib4/http2/flow_control.py
urllib4/http2/probe.py
urllib4/http2/push.py
urllib4/http2/push_manager.py
urllib4/http2/settings.py
urllib4/http3/__init__.py
urllib4/http3/connection.py
urllib4/http3/migration.py
urllib4/http3/multipath.py
urllib4/http3/settings.py
urllib4/util/__init__.py
urllib4/util/cert_transparency.py
urllib4/util/cert_verification.py
urllib4/util/connection.py
urllib4/util/hsts.py
urllib4/util/proxy.py
urllib4/util/request.py
urllib4/util/response.py
urllib4/util/retry.py
urllib4/util/ssl_.py
urllib4/util/ssltransport.py
urllib4/util/timeout.py
urllib4/util/url.py
urllib4/util/util.py
urllib4/websocket/__init__.py
urllib4/websocket/backpressure.py
urllib4/websocket/connection.py
urllib4/websocket/exceptions.py
urllib4/websocket/extensions.py
urllib4/websocket/health.py
urllib4/websocket/protocol.py
urllib4/websocket/subprotocols.py
urllib4_enhanced-1.1.2.dist-info/licenses/LICENSE.txt
urllib4_enhanced-1.1.2.dist-info/METADATA
urllib4_enhanced-1.1.2.dist-info/WHEEL
urllib4_enhanced-1.1.2.dist-info/top_level.txt
urllib4_enhanced-1.1.2.dist-info/RECORD
