Metadata-Version: 2.4
Name: urllib4-enhanced
Version: 1.1.2
Summary: A modern HTTP client for Python with HTTP/3, WebSocket extensions, and enhanced security features
Home-page: https://github.com/zinzied/urllib4-enhanced
Author: Zied Boughdir
Author-email: Zied Boughdir <ziedboughdir@gmail.com>
License-Expression: MIT
Project-URL: Documentation, https://github.com/zinzied/urllib4
Project-URL: Code, https://github.com/zinzied/urllib4
Project-URL: Issue tracker, https://github.com/zinzied/urllib4/issues
Keywords: urllib,httplib,threadsafe,filepost,http,https,ssl,pooling,http2,http3,quic,websocket,security
Classifier: Environment :: Web Environment
Classifier: Intended Audience :: Developers
Classifier: Operating System :: OS Independent
Classifier: Programming Language :: Python
Classifier: Programming Language :: Python :: 3
Classifier: Programming Language :: Python :: 3.7
Classifier: Programming Language :: Python :: 3.8
Classifier: Programming Language :: Python :: 3.9
Classifier: Programming Language :: Python :: 3.10
Classifier: Programming Language :: Python :: 3.11
Classifier: Programming Language :: Python :: 3.12
Classifier: Programming Language :: Python :: 3 :: Only
Classifier: Programming Language :: Python :: Implementation :: CPython
Classifier: Programming Language :: Python :: Implementation :: PyPy
Classifier: Topic :: Internet :: WWW/HTTP
Classifier: Topic :: Software Development :: Libraries
Requires-Python: >=3.7
License-File: LICENSE.txt
Provides-Extra: brotli
Requires-Dist: brotli>=1.0.9; platform_python_implementation == "CPython" and extra == "brotli"
Requires-Dist: brotlicffi>=0.8.0; platform_python_implementation != "CPython" and extra == "brotli"
Provides-Extra: zstd
Requires-Dist: zstandard>=0.18.0; extra == "zstd"
Provides-Extra: socks
Requires-Dist: PySocks!=1.5.7,<2.0,>=1.5.6; extra == "socks"
Provides-Extra: http2
Requires-Dist: h2<5,>=4; extra == "http2"
Provides-Extra: http3
Requires-Dist: aioquic>=0.9.20; extra == "http3"
Requires-Dist: netifaces>=0.11.0; extra == "http3"
Provides-Extra: websocket
Requires-Dist: idna>=2.0.0; extra == "websocket"
Requires-Dist: msgpack>=1.0.4; extra == "websocket"
Requires-Dist: cbor2>=5.4.6; extra == "websocket"
Provides-Extra: security
Requires-Dist: cryptography>=38.0.0; extra == "security"
Provides-Extra: all
Requires-Dist: brotli>=1.0.9; platform_python_implementation == "CPython" and extra == "all"
Requires-Dist: brotlicffi>=0.8.0; platform_python_implementation != "CPython" and extra == "all"
Requires-Dist: zstandard>=0.18.0; extra == "all"
Requires-Dist: PySocks!=1.5.7,<2.0,>=1.5.6; extra == "all"
Requires-Dist: h2<5,>=4; extra == "all"
Requires-Dist: aioquic>=0.9.20; extra == "all"
Requires-Dist: netifaces>=0.11.0; extra == "all"
Requires-Dist: msgpack>=1.0.4; extra == "all"
Requires-Dist: cbor2>=5.4.6; extra == "all"
Requires-Dist: cryptography>=38.0.0; extra == "all"
Dynamic: author
Dynamic: home-page
Dynamic: license-file
Dynamic: requires-python
